Quantitative_Sciences/Computer_Science/Architecture/code/sr_latch.v
// Gated D Latch
module gated_d_latch (
    input D, EN,
    output Q, Qn
);

wire S, R;

and (S, D, EN);
and (R, ~D, EN);
nor (Qn, R, Q);
nor (Q, S, Qn);

endmodule

// Testbench
module tb;

reg D, EN;
wire Q, Qn;

gated_d_latch dut (D, EN, Q, Qn);

initial begin
    $dumpfile("gated_d_latch.vcd");
    $dumpvars(0, tb);
    
    // Initialize
    D = 0; EN = 0; #5;
    
    // Test pattern matching the waveform
    D = 1; EN = 0; #10;  // D high, EN low
    D = 0; EN = 0; #10;  // D low, EN low
    D = 1; EN = 0; #5;   // D high, EN low
    D = 0; EN = 1; #5;   // D low, EN high
    D = 1; EN = 1; #10;  // D high, EN high
    D = 0; EN = 1; #10;  // D low, EN high
    D = 1; EN = 1; #15;  // D high, EN high
    D = 0; EN = 0; #5;   // D low, EN low
    D = 1; EN = 0; #10;  // D high, EN low
    D = 0; EN = 1; #10;  // D low, EN high
    D = 1; EN = 1; #5;   // D high, EN high
    D = 0; EN = 1; #5;   // D low, EN high
    D = 1; EN = 0; #10;  // D high, EN low
    D = 0; EN = 0; #5;   // D low, EN low
    
    $finish;
end

endmodule

STEM/Computer_Science/Architecture/code/gated_d_latch.vcd
$date
	Fri May 23 23:24:21 2025
$end
$version
	Icarus Verilog
$end
$timescale
	1s
$end
$scope module tb $end
$var wire 1 ! Qn $end
$var wire 1 " Q $end
$var reg 1 # D $end
$var reg 1 $ EN $end
$scope module dut $end
$var wire 1 # D $end
$var wire 1 $ EN $end
$var wire 1 " Q $end
$var wire 1 ! Qn $end
$var wire 1 % R $end
$var wire 1 & S $end
$upscope $end
$upscope $end
$enddefinitions $end
$comment Show the parameter values. $end
$dumpall
$end
#0
$dumpvars
0&
0%
0$
0#
x"
x!
$end
#5
1#
#15
0#
#25
1#
#30
1"
0!
1%
1$
0#
#35
1!
0"
0%
1&
1#
#45
1"
0!
1%
0&
0#
#55
1!
0"
0%
1&
1#
#70
0&
0$
0#
#75
1#
#85
1"
0!
1%
1$
0#
#95
1!
0"
0%
1&
1#
#100
1"
0!
1%
0&
0#
#105
0%
0$
1#
#115
0#
