STEM/Computer_Science/Architecture/code/and.v
module multiplex_gate_level(A, B, X, out1);
  input A, B, X;
  output out1;

  wire not_x;
  wire out_and1, out_and2;

  not not1(not_X, X);
  and and1(out_and1, not_X, A);
  and and2(out_and2, X, B);
  or or1(out1, out_and1, out_and2);
endmodule

module tb_multiplex;
  reg A, B, X;
  wire out1;

  multiplex_gate_level uut(A, B, X, out1);

  initial begin
    // Test all combinations
    A = 0; B = 0; X = 0; #10;
    A = 0; B = 1; X = 0; #10;
    A = 1; B = 0; X = 0; #10;
    A = 1; B = 1; X = 0; #10;
    A = 0; B = 0; X = 1; #10;
    A = 0; B = 1; X = 1; #10;
    A = 1; B = 0; X = 1; #10;
    A = 1; B = 1; X = 1; #10;
    $finish;
  end

  initial begin
    $dumpfile("waves.vcd");
    $dumpvars(0, tb_multiplex);
  end
endmodule

STEM/Computer_Science/Architecture/code/waves.vcd
$date
	Fri May 23 02:42:28 2025
$end
$version
	Icarus Verilog
$end
$timescale
	1s
$end
$scope module tb_multiplex $end
$var wire 1 ! out1 $end
$var reg 1 " A $end
$var reg 1 # B $end
$var reg 1 $ X $end
$scope module uut $end
$var wire 1 " A $end
$var wire 1 # B $end
$var wire 1 $ X $end
$var wire 1 % not_X $end
$var wire 1 ! out1 $end
$var wire 1 & out_and1 $end
$var wire 1 ' out_and2 $end
$upscope $end
$upscope $end
$enddefinitions $end
$comment Show the parameter values. $end
$dumpall
$end
#0
$dumpvars
0'
0&
1%
0$
0#
0"
0!
$end
#10
1#
#20
1!
1&
0#
1"
#30
1#
#40
0!
0%
0&
1$
0#
0"
#50
1!
1'
1#
#60
0!
0'
0#
1"
#70
1!
1'
1#
